{"cameraMode":{"drawMode":0,"name":"Shaded","section":"Shading Mode"},"sceneLighting":true,"audioPlay":false,"sceneViewState":{"m_AlwaysRefresh":false,"showFog":true,"showSkybox":true,"showFlares":true,"showImageEffects":true,"showParticleSystems":true,"showVisualEffectGraphs":true,"m_FxEnabled":true},"in2DMode":false,"pivot":{"x":16.55533790588379,"y":3.349790334701538,"z":54.16061019897461},"rotation":{"x":0.3227927088737488,"y":0.6309857368469238,"z":-0.3260253071784973,"w":0.6257199645042419},"size":1.7268693447113038,"orthographic":false}